Codes 3-1/CA/Demo/decoder_3to8.v
module decoder_3to8 (
    input [2:0] A,       // 3-bit input
    output reg [7:0] Y   // 8-bit output
);

    always @(*) begin
        case (A)
            3'b000: Y = 8'b00000001;  // Output 0 is active
            3'b001: Y = 8'b00000010;  // Output 1 is active
            3'b010: Y = 8'b00000100;  // Output 2 is active
            3'b011: Y = 8'b00001000;  // Output 3 is active
            3'b100: Y = 8'b00010000;  // Output 4 is active
            3'b101: Y = 8'b00100000;  // Output 5 is active
            3'b110: Y = 8'b01000000;  // Output 6 is active
            3'b111: Y = 8'b10000000;  // Output 7 is active
            default: Y = 8'b00000000; // Default case (shouldn't happen)
        endcase
    end

endmodule

Codes 3-1/CA/Demo/tb_decoder_3to8.v
`timescale 1ns/1ns

module tb_decoder_3to8;

    reg [2:0] A;          // 3-bit input
    wire [7:0] Y;         // 8-bit output

    // Instantiate the 3-to-8 decoder
    decoder_3to8 uut (
        .A(A),
        .Y(Y)
    );

    initial begin
        // Open VCD file for waveform analysis
        $dumpfile("test.vcd");
        $dumpvars(0, tb_decoder_3to8);

        // Apply test cases
        A = 3'b000; #10; // Test input 0
        A = 3'b001; #10; // Test input 1
        A = 3'b010; #10; // Test input 2
        A = 3'b011; #10; // Test input 3
        A = 3'b100; #10; // Test input 4
        A = 3'b101; #10; // Test input 5
        A = 3'b110; #10; // Test input 6
        A = 3'b111; #10; // Test input 7

        // End simulation
        $finish;
    end

    // Monitor the inputs and outputs
    initial begin
        $monitor("Time = %0t | A = %b | Y = %b", $time, A, Y);
    end

endmodule

Codes 3-1/CA/Demo/test.vcd
$date
	Sat Oct 05 10:12:51 2024
$end
$version
	Icarus Verilog
$end
$timescale
	1ns
$end
$scope module tb_decoder_3to8 $end
$var wire 8 ! Y [7:0] $end
$var reg 3 " A [2:0] $end
$scope module uut $end
$var wire 3 # A [2:0] $end
$var reg 8 $ Y [7:0] $end
$upscope $end
$upscope $end
$enddefinitions $end
$comment Show the parameter values. $end
$dumpall
$end
#0
$dumpvars
b1 $
b0 #
b0 "
b1 !
$end
#10
b10 !
b10 $
b1 "
b1 #
#20
b100 !
b100 $
b10 "
b10 #
#30
b1000 !
b1000 $
b11 "
b11 #
#40
b10000 !
b10000 $
b100 "
b100 #
#50
b100000 !
b100000 $
b101 "
b101 #
#60
b1000000 !
b1000000 $
b110 "
b110 #
#70
b10000000 !
b10000000 $
b111 "
b111 #
